{
	"type": "modal",
	"title": {
		"type": "plain_text",
		"text": "Tyke Login",
		"emoji": true
	},
	"close": {
		"type": "plain_text",
		"text": "Close",
		"emoji": true
	},
	"blocks": [
		{
			"type": "section",
			"text": {
				"type": "mrkdwn",
				"text": "Please login to start using tyke application"
			},
			"accessory": {
				"type": "button",
				"text": {
					"type": "plain_text",
					"text": "Login",
					"emoji": true
				},
				"value": "click_me_123",
				"url": "https://test.tyke.ai/slack/login",
				"action_id": "button-action"
			}
		}
	]
}